__init__.py
quickcolor/__init__.py
quickcolor/color_cli.py
quickcolor/color_def.py
quickcolor/color_filter.py
quickcolor/color_show.py
quickcolor-0.1.3.dist-info/LICENSE
quickcolor-0.1.3.dist-info/METADATA
quickcolor-0.1.3.dist-info/WHEEL
quickcolor-0.1.3.dist-info/entry_points.txt
quickcolor-0.1.3.dist-info/top_level.txt
quickcolor-0.1.3.dist-info/RECORD
