Metadata-Version: 2.1
Name: quickcolor
Version: 0.1.3
Summary: Ascii text color code tagging for python prints and logs
Author-email: Ed Waldner <waldevburry@proton.me>
Maintainer-email: Ed Waldner <waldevburry@proton.me>
Project-URL: Homepage, https://github.com/ew98/quickcolor
Project-URL: Documentation, https://github.com/ew98/quickcolor/wiki/QuickColor
Project-URL: Issues, https://github.com/ew98/quickcolor/issues
Keywords: util,utility
Classifier: Development Status :: 3 - Alpha
Classifier: Environment :: Console
Classifier: Intended Audience :: Developers
Classifier: License :: OSI Approved :: MIT License
Classifier: Natural Language :: English
Classifier: Programming Language :: Python :: 3.9
Classifier: Programming Language :: Python :: 3.10
Classifier: Programming Language :: Python :: 3.11
Classifier: Programming Language :: Python :: 3.12
Classifier: Operating System :: OS Independent
Classifier: Topic :: Utilities
Requires-Python: >=3.9
License-File: LICENSE
Requires-Dist: argcomplete
